evoaug_tf/__init__.py
evoaug_tf/augment.py
evoaug_tf/evoaug.py
evoaug_tf-1.0.0.dist-info/LICENSE
evoaug_tf-1.0.0.dist-info/METADATA
evoaug_tf-1.0.0.dist-info/WHEEL
evoaug_tf-1.0.0.dist-info/top_level.txt
evoaug_tf-1.0.0.dist-info/RECORD
