Metadata-Version: 2.1
Name: evoaug-tf
Version: 1.0.0
Summary: A Python package that trains models with evolution-inspired data augmentations. 
Home-page: UNKNOWN
License: UNKNOWN
Platform: UNKNOWN
Requires-Python: >=3.6
License-File: LICENSE
